__init__.py
example.py
test.py
twitter_hashtag_scraper.py
utils_beautiful_soup.py
utils_json.py
twitter_hashtag_scraper-1.2.2.dist-info/METADATA
twitter_hashtag_scraper-1.2.2.dist-info/WHEEL
twitter_hashtag_scraper-1.2.2.dist-info/license.txt
twitter_hashtag_scraper-1.2.2.dist-info/top_level.txt
twitter_hashtag_scraper-1.2.2.dist-info/RECORD
