Metadata-Version: 2.1
Name: twitter-hashtag-scraper
Version: 1.2.2
Summary: Unofficial Twitter Hashtag Scraper using free proxies
Home-page: https://github.com/jorgeramirezcarrasco/twitter-hashtag-scraper
Author: Jorge Ramírez Carrasco
License: UNKNOWN
Keywords: twitter,web scraping
Platform: UNKNOWN
Requires-Python: >=3.6, <4
Requires-Dist: beautifulsoup4 (>=4.9.1)
Requires-Dist: certifi (>=2020.6.20)
Requires-Dist: chardet (>=3.0.4)
Requires-Dist: idna (>=2.10)
Requires-Dist: lxml (>=4.5.2)
Requires-Dist: numpy (>=1.19.1)
Requires-Dist: pandas (>=1.1.0)
Requires-Dist: python-dateutil (>=2.8.1)
Requires-Dist: pytz (>=2020.1)
Requires-Dist: requests (>=2.24.0)
Requires-Dist: six (>=1.15.0)
Requires-Dist: soupsieve (>=2.0.1)
Requires-Dist: urllib3 (>=1.25.10)
